interactive_feedback_mcp/__init__.py
interactive_feedback_mcp/feedback_ui.py
interactive_feedback_mcp/server.py
interactive_feedback_mcp-0.1.2.dist-info/licenses/LICENSE
interactive_feedback_mcp-0.1.2.dist-info/METADATA
interactive_feedback_mcp-0.1.2.dist-info/WHEEL
interactive_feedback_mcp-0.1.2.dist-info/entry_points.txt
interactive_feedback_mcp-0.1.2.dist-info/top_level.txt
interactive_feedback_mcp-0.1.2.dist-info/RECORD
