Metadata-Version: 2.4
Name: interactive-feedback-mcp
Version: 0.1.2
Summary: MCP server for interactive user feedback and command execution in AI-assisted development, by Fábio Ferreira.
Requires-Python: >=3.11
License-File: LICENSE
Requires-Dist: fastmcp>=2.0.0
Requires-Dist: psutil>=7.0.0
Requires-Dist: pyside6>=6.8.2.1
Requires-Dist: pillow
Dynamic: license-file
